{
 	"rooms": {
		"mcsw-vestibule": {
			"name": "Foyer",
			"type": "jitsi",
			"description": "Welcome!",
			"backgroundImage": "js/images/rooms/vestibule.jpg",
			"directions": {
				"north": "mcsw-closet",
				"west": "mcsw-skribbl",
				"east": "mcsw-codenames"
			},
			"map": {
				"x": 16,
				"y": 19,
				"width": 5,
				"height": 3,
				"doors": {
					"north": 18,
					"west": 20,
					"east": 20
				}
			}
		},
		"mcsw-closet": {
			"name": "Closet",
			"type": "jitsi",
			"capacity": 2,
			"backgroundImage": "js/images/rooms/closet.jpg",
			"description": "A quiet, cozy closet. Shhh.",
			"directions": {
				"south": "mcsw-vestibule"
			},
			"map": {
				"x": 18,
				"y": 18,
				"width": 2,
				"height": 1,
				"doors": {
					"south": 18
				}
			}
		},
		"mcsw-codenames": {
			"name": "Codenames",
			"type": "iframe",
			"directions": {
				"west": "mcsw-vestibule"
			},
			"iframeOptions": {
				"src": "https://www.horsepaste.com/nutritional-london"
			},
			"map": {
				"x": 21,
				"y": 19,
				"width": 6,
				"height": 3,
				"doors": {
					"west": 20
				}
			},
			"doorTint": "orange",
			"backgroundImage": "js/images/rooms/livingroom.jpg"
		},
		"mcsw-skribbl": {
			"name": "Skribbl",
			"type": "iframe",
			"directions": {
				"east": "mcsw-vestibule"
			},
			"iframeOptions": {
				"src": "https://skribbl.io/?hQYvEpnHK6sO"
			},
			"map": {
				"x": 10,
				"y": 19,
				"width": 6,
				"height": 3,
				"doors": {
					"east": 20
				}
			},
			"doorTint": "orange",
			"backgroundImage": "js/images/rooms/livingroom.jpg"
		}
	}
}
